fakeit/__init__.py
fakeit/advanced/__init__.py
fakeit/advanced/person/__init__.py
fakeit/basics/__init__.py
fakeit/basics/boolean/__init__.py
fakeit/basics/bytes/__init__.py
fakeit/basics/geo/__init__.py
fakeit/basics/geo/address.py
fakeit/basics/geo/ip.py
fakeit/basics/geo/named.py
fakeit/basics/geo/position.py
fakeit/basics/hashes/__init__.py
fakeit/basics/ip/__init__.py
fakeit/basics/ip/v4.py
fakeit/basics/ip/v6.py
fakeit/basics/numerics/__init__.py
fakeit/basics/personal/__init__.py
fakeit/basics/personal/emails.py
fakeit/basics/personal/names.py
fakeit/basics/personal/phones.py
fakeit/basics/strings/__init__.py
fakeit/basics/texts/__init__.py
fakeit/basics/texts/lorem.py
fakeit/basics/uuids/__init__.py
fakeit/constance/__init__.py
fakeit/constance/email/__init__.py
fakeit/constance/tld/__init__.py
fakeit/exceptions.py
fakeit/extras/__init__.py
fakeit/extras/alchemy/__init__.py
fakeit/extras/alchemy/utils.py
fakeit/extras/django/__init__.py
fakeit-0.1.10.dist-info/LICENSE
fakeit-0.1.10.dist-info/WHEEL
fakeit-0.1.10.dist-info/METADATA
fakeit-0.1.10.dist-info/RECORD
