Metadata-Version: 2.1
Name: fakeit
Version: 0.1.10
Summary: Generate fake data
License: MIT
Author: Ruslan Samoylov
Author-email: ruslan.v.samoylov@gmail.com
Requires-Python: >=3.6
Classifier: License :: OSI Approved :: MIT License
Classifier: Programming Language :: Python :: 3
Classifier: Programming Language :: Python :: 3.6
Classifier: Programming Language :: Python :: 3.7
Classifier: Programming Language :: Python :: 3.8
Provides-Extra: all
Provides-Extra: django
Provides-Extra: pydantic
Provides-Extra: sqlalchemy
Project-URL: homepage, https://github.com/RCheese/fakeit
Project-URL: issues, https://github.com/RCheese/fakeit/issues
